<?xml version="1.0" encoding="UTF-8"?>
<knimeNode icon="./default.png" type="Source" xmlns="http://knime.org/node/v2.8" xmlns:xsi="http://www.w3.org/2001/XMLSchema-instance" xsi:schemaLocation="http://knime.org/node/v2.8 http://knime.org/node/v2.8.xsd">
    <name>JSON Reader</name>
    
    <shortDescription>
        Reads .json to JSON values.
    </shortDescription>
    
    <fullDescription>
        <intro>Reads the .json files and parse them as JSON values.</intro>
        
        
        <option name="Location">The path to the file to read (supports remote and .json.gz files too)</option>
        <option name="Output column name">Name of the output column</option>
        <option name="Select with JSON Pointer">Select a part of the read JSON if checked</option>
        <option name="JSON Pointer">The part to select from the input JSON. <a href="http://tools.ietf.org/html/rfc6901">JSONPointer</a></option>
        <option name="Fail if pointer not found">If checked, execution will fail if no such part found. If unchecked and not found, the result will be an missing value.</option>
        <option name="Allow comments in json files"><tt>/*</tt>...<tt>*/</tt> and the line comments <tt>//</tt>, <tt>#</tt> are interpreted as comments and get ignored instead of causing errors when this option is selected</option>
        <!-- possibly more options that can also be grouped by tabs -->
        <!--
        <tab name="Standard Options">
            <option name="short name of first option (like in the dialog)">description of first option</option>
            <option name="short name of second option (like in the dialog)">description of second option</option>
        </tab>
        <tab name="Advanced Options">
            <option name="short name of first advanced option (like in the dialog)">description of first advanced option</option>
        </tab>
        -->
    </fullDescription>
    
    <ports>
        <outPort index="0" name="JSON table">Table with the read JSON values</outPort>
    </ports>    
</knimeNode>
